lesa/__init__.py
lesa/cli/__init__.py
lesa/cli/main.py
lesa/core/__init__.py
lesa/core/conversations.py
lesa/core/directory_manager.py
lesa/core/ollama.py
lesa/samples/documents/Microprocessor.pdf
lesa/samples/documents/Research Paper on Attitute of Urban and Rural College students.pdf
lesa/samples/documents/fine-tuning-deck.pdf
lesa/samples/documents/story-sample-1.pdf
lesa/scratch/main.py
lesa/scratch/notebook.ipynb
lesa/tests/__init__.py
lesa/utils/__init__.py
lesa/utils/pre_prompt.py
lesa-0.1.0.7.dist-info/LICENSE
lesa-0.1.0.7.dist-info/METADATA
lesa-0.1.0.7.dist-info/WHEEL
lesa-0.1.0.7.dist-info/entry_points.txt
lesa-0.1.0.7.dist-info/RECORD
