Metadata-Version: 2.1
Name: lesa
Version: 0.1.0.7
Summary: A CLI tool to converse with any document locally using Ollama.
Home-page: https://github.com/shxntanu/lesa
License: Apache-2.0
Keywords: lesa,rag pipeline,document chatbot
Author: Shantanu Wable
Author-email: shantanuwable2003@gmail.com
Requires-Python: >=3.10.14,<3.13
Classifier: License :: OSI Approved :: Apache Software License
Classifier: Operating System :: MacOS
Classifier: Operating System :: Unix
Classifier: Programming Language :: Python :: 3
Classifier: Programming Language :: Python :: 3.11
Classifier: Topic :: Software Development :: Libraries :: Python Modules
Requires-Dist: docx2txt (>=0.8,<0.9)
Requires-Dist: faiss-cpu (>=1.9.0.post1,<2.0.0)
Requires-Dist: langchain (>=0.3.13,<0.4.0)
Requires-Dist: langchain-community (>=0.3.13,<0.4.0)
Requires-Dist: langchain-huggingface (>=0.1.2,<0.2.0)
Requires-Dist: langchain-ollama (>=0.2.2,<0.3.0)
Requires-Dist: markdown-it-py (>=3.0.0,<4.0.0)
Requires-Dist: mdit-plain (>=1.0.1,<2.0.0)
Requires-Dist: ollama (>=0.4.2,<0.5.0)
Requires-Dist: pandas (>=2.2.3,<3.0.0)
Requires-Dist: platformdirs (>=4.3.6,<5.0.0)
Requires-Dist: psutil (>=6.1.0,<7.0.0)
Requires-Dist: pypdf (>=5.1.0,<6.0.0)
Requires-Dist: python-docx (>=1.1.2,<2.0.0)
Requires-Dist: requests (>=2.32.3,<3.0.0)
Requires-Dist: rich (>=13.9.4,<14.0.0)
Requires-Dist: sentence-transformers (>=3.3.1,<4.0.0)
Requires-Dist: six (>=1.16.0,<2.0.0)
Requires-Dist: torch (>=2.5.1,<3.0.0)
Requires-Dist: typer (>=0.14.0,<0.15.0)
Project-URL: Repository, https://github.com/shxntanu/lesa
